peplum/__init__.py
peplum/__main__.py
peplum/py.typed
peplum/app/__init__.py
peplum/app/peplum.py
peplum/app/commands/__init__.py
peplum/app/commands/filtering.py
peplum/app/commands/finding.py
peplum/app/commands/main.py
peplum/app/commands/navigation_sorting.py
peplum/app/commands/peps_sorting.py
peplum/app/data/__init__.py
peplum/app/data/config.py
peplum/app/data/locations.py
peplum/app/data/notes.py
peplum/app/data/pep.py
peplum/app/data/peps.py
peplum/app/messages/__init__.py
peplum/app/messages/main.py
peplum/app/providers/__init__.py
peplum/app/providers/authors.py
peplum/app/providers/main.py
peplum/app/providers/peps.py
peplum/app/providers/python_versions.py
peplum/app/providers/statuses.py
peplum/app/providers/types.py
peplum/app/screens/__init__.py
peplum/app/screens/main.py
peplum/app/screens/notes_editor.py
peplum/app/screens/pep_viewer.py
peplum/app/widgets/__init__.py
peplum/app/widgets/navigation.py
peplum/app/widgets/pep_details.py
peplum/app/widgets/peps_view.py
peplum/peps/__init__.py
peplum/peps/api.py
peplum-1.0.1.dist-info/METADATA
peplum-1.0.1.dist-info/WHEEL
peplum-1.0.1.dist-info/entry_points.txt
peplum-1.0.1.dist-info/licenses/LICENSE
peplum-1.0.1.dist-info/RECORD
