Metadata-Version: 2.3
Name: peplum
Version: 1.0.1
Summary: A terminal-based PEP lookup manager
Project-URL: Homepage, https://peplum.davep.dev/
Project-URL: Repository, https://github.com/davep/peplum
Project-URL: Documentation, https://peplum.davep.dev/
Project-URL: Source, https://github.com/davep/peplum
Project-URL: Issues, https://github.com/davep/peplum/issues
Project-URL: Discussions, https://github.com/davep/peplum/discussions
Author-email: Dave Pearson <davep@davep.org>
License: GNU General Public License v3 or later (GPLv3+)
Keywords: chui,documentation,pep,terminal,tui
Classifier: Development Status :: 5 - Production/Stable
Classifier: Environment :: Console
Classifier: Intended Audience :: Developers
Classifier: Intended Audience :: End Users/Desktop
Classifier: Intended Audience :: Information Technology
Classifier: License :: OSI Approved :: GNU General Public License v3 or later (GPLv3+)
Classifier: Natural Language :: English
Classifier: Operating System :: OS Independent
Classifier: Programming Language :: Python :: 3
Classifier: Programming Language :: Python :: 3 :: Only
Classifier: Programming Language :: Python :: 3.10
Classifier: Programming Language :: Python :: 3.11
Classifier: Programming Language :: Python :: 3.12
Classifier: Programming Language :: Python :: 3.13
Classifier: Topic :: Documentation
Classifier: Topic :: Education
Classifier: Topic :: Software Development
Classifier: Topic :: Software Development :: Documentation
Classifier: Topic :: Terminals
Classifier: Topic :: Utilities
Classifier: Typing :: Typed
Requires-Python: >=3.10
Requires-Dist: httpx>=0.28.1
Requires-Dist: humanize>=4.11.0
Requires-Dist: packaging>=24.2
Requires-Dist: textual-enhanced>=0.13.0
Requires-Dist: textual-fspicker>=0.4.0
Requires-Dist: textual>=3.1.1
Requires-Dist: typing-extensions>=4.12.2
Requires-Dist: xdg-base-dirs>=6.0.2
